{
	"offerList" : [
		{
			"vector" : "tnt",
			"typeMa" : 24,
			"productList" : [
				{
					"code" : "2003",
					"label" : "CANAL+ Multiécrans AX"
				},
				{
					"code" : "2004",
					"label" : "CANAL+ TECH PVR"
				},
				{
					"code" : "221",
					"label" : "MINIPACK TNT"
				},
				{
					"code" : "550",
					"label" : "Tunnel CSAT"
				},
				{
					"code" : "4220",
					"label" : "CSAT Panorama"
				},
				{
					"code" : "4223",
					"label" : "Pack Ciné Séries HX"
				}, 
				{
					"code" : "4226",
					"label" : "Pack Ciné Séries AX"
				},
				{
					"code" : "4229",
					"label" : "Pano Séries Ciné HX"
				},
				{
					"code" : "4232",
					"label" : "Pano Séries Ciné AX"
				}
			]
		},
		{
			"vector" : "fibre",
			"typeMa" : 86,
			"productList": [
				{
					"code" : "6100",
					"label" : "TV-Fibre"
				},
				{
					"code" : "4061",
					"label" : "CANAL+ AX"
				},
				{
					"code" : "1810",
					"label" : "Panorama"
				}
			]
		},
		{
			"vector" : "sat",
			"typeMa" : 18,
			"productList": [
				{
					"code" : "xxxx",
					"label" : "Dummy Offer 1"
				},
				{
					"code" : "yyyy",
					"label" : "Dummy Offer 2"
				}
			]
		}
	]
}